{
  "projectName": "CloudStrollOffice",
  "version": "v0.1.6",
  "prd": "docs/prds/CloudStrollOffice-prd-v0.1.6.md",
  "sds": "docs/sds/CloudStrollOffice-sds-v0.1.6.md",
  "architecture": "docs/architecture.md",
  "project": "docs/project.md",
  "require": "docs/requires/CloudStrollOffice-requirement-v0.1.6.md",
  "tasks": [
    {
      "id": "TASK-001",
      "title": "新增 RegisterModeEnum 注册模式枚举",
      "description": "在 cloudoffice-common 模块的 common.enums 包下新增 RegisterModeEnum 枚举，包含 USERNAME/PHONE_CODE/OAUTH/PHONE_SET_USERNAME/OAUTH_SET_INFO 等5个枚举值，每个包含 code/label/requiresPhone 属性，提供 fromCode 静态方法。",
      "taskType": "common",
      "userStoryIds": ["US-001"],
      "upstreamTaskIds": [],
      "downstreamTaskIds": ["TASK-007", "TASK-022"],
      "priority": "P0",
      "status": "pending",
      "testMethod": "单元测试覆盖5个枚举值属性正确性、fromCode有效/无效/null场景；验证 mvn clean compile -pl cloudoffice-common 编译通过",
      "contextObtain": "PRD v0.1.6 US-001「注册登录模式枚举」章节；SDS v0.1.6 2.2.1 节 cloudoffice-common 公共模块新增内容；需求文档 FR-001"
    },
    {
      "id": "TASK-002",
      "title": "新增 LoginModeEnum 登录模式枚举",
      "description": "在 cloudoffice-common 模块的 common.enums 包下新增 LoginModeEnum 枚举，包含 USERNAME_PASSWORD/PHONE_CODE/PHONE_PASSWORD/OAUTH 等4个枚举值，每个包含 code/label 属性，提供 fromCode 静态方法。",
      "taskType": "common",
      "userStoryIds": ["US-001"],
      "upstreamTaskIds": [],
      "downstreamTaskIds": ["TASK-006", "TASK-017"],
      "priority": "P0",
      "status": "pending",
      "testMethod": "单元测试覆盖4个枚举值属性正确性、fromCode有效/无效/null场景；验证编译通过",
      "contextObtain": "PRD v0.1.6 US-001「注册登录模式枚举」章节；需求文档 FR-001"
    },
    {
      "id": "TASK-003",
      "title": "新增 OAuthProviderEnum OAuth提供商枚举",
      "description": "在 cloudoffice-common 模块的 common.enums 包下新增 OAuthProviderEnum 枚举，包含 WECHAT/DINGTALK/WECHAT_WORK/ALIPAY 等4个枚举值，每个包含 code/label 属性，提供 fromCode 静态方法。",
      "taskType": "common",
      "userStoryIds": ["US-003"],
      "upstreamTaskIds": [],
      "downstreamTaskIds": ["TASK-006", "TASK-007", "TASK-021", "TASK-025", "TASK-027"],
      "priority": "P1",
      "status": "pending",
      "testMethod": "单元测试覆盖4个枚举值属性正确性、fromCode有效/无效/null场景；验证编译通过",
      "contextObtain": "PRD v0.1.6 US-003「OAuth 提供商枚举」章节；需求文档 FR-003"
    },
    {
      "id": "TASK-004",
      "title": "ErrorCode枚举扩展（AUTH-0020~AUTH-0033）",
      "description": "在现有 ErrorCode 枚举中新增14个认证增强错误码：AUTH-0020 PASSWORD_RESET_TOKEN_INVALID 至 AUTH-0033 LOGIN_MODE_INVALID。不可删除或修改现有错误码。每个新枚举常量需带有 AUTH-XXXX 格式注释。",
      "taskType": "common",
      "userStoryIds": ["US-002"],
      "upstreamTaskIds": [],
      "downstreamTaskIds": ["TASK-018", "TASK-019", "TASK-020", "TASK-021", "TASK-023", "TASK-024", "TASK-025", "TASK-026", "TASK-027", "TASK-028", "TASK-029", "TASK-031", "TASK-032", "TASK-033"],
      "priority": "P0",
      "status": "pending",
      "testMethod": "单元测试验证14个新增错误码的存在性、getCode()/getMessage()返回正确；验证现有19个错误码未被修改",
      "contextObtain": "PRD v0.1.6 US-002「认证错误码扩展」章节+附录5.3错误码速查表；SDS v0.1.6 4.3节错误码定义；需求文档 FR-002；现有 ErrorCode.java"
    },
    {
      "id": "TASK-005",
      "title": "RedisKeyConstants 验证码相关Key扩展",
      "description": "在 RedisKeyConstants 常量类中新增验证码缓存Key 'auth:verification:{purpose}:{target}' 和频率控制Key 'auth:verification:freq:{purpose}:{target}'，并提供对应的 Key 构建静态方法。",
      "taskType": "common",
      "userStoryIds": ["US-016"],
      "upstreamTaskIds": [],
      "downstreamTaskIds": ["TASK-029"],
      "priority": "P0",
      "status": "pending",
      "testMethod": "单元测试验证 Key 常量正确性和 Key 构建方法输出格式",
      "contextObtain": "SDS v0.1.6 3.3.1节 Redis Key设计（v0.1.6新增），5.5节 Redis Key设计表；需求文档 FR-016"
    },
    {
      "id": "TASK-006",
      "title": "LoginRequest DTO修改（增加loginMode等字段）",
      "description": "修改 LoginRequest DTO，新增 loginMode/phone/smsCode/oauthProvider/oauthCode 字段。loginName 和 password 改为可选（条件必填）。保留 tenantCode 和 clientType。向后兼容：loginMode 不传时默认 USERNAME_PASSWORD。",
      "taskType": "backend",
      "userStoryIds": ["US-004"],
      "upstreamTaskIds": ["TASK-002", "TASK-003"],
      "downstreamTaskIds": ["TASK-017", "TASK-018", "TASK-019", "TASK-020", "TASK-021", "TASK-032"],
      "priority": "P0",
      "status": "pending",
      "testMethod": "单元测试验证所有字段的getter/setter/Builder/序列化；验证向后兼容性",
      "contextObtain": "PRD v0.1.6 US-004 AC1；SDS v0.1.6 4.2.1节请求参数表格；需求文档 FR-004(1)"
    },
    {
      "id": "TASK-007",
      "title": "RegisterRequest DTO修改（增加registerMode等字段）",
      "description": "修改 RegisterRequest DTO，新增 registerMode/smsCode/oauthProvider/oauthCode 字段。移除 tenantId 字段。字段按模式改为可选。向后兼容：registerMode 不传时默认 USERNAME。",
      "taskType": "backend",
      "userStoryIds": ["US-004"],
      "upstreamTaskIds": ["TASK-001", "TASK-003"],
      "downstreamTaskIds": ["TASK-022", "TASK-023", "TASK-024", "TASK-025", "TASK-026", "TASK-027", "TASK-032"],
      "priority": "P0",
      "status": "pending",
      "testMethod": "单元测试验证所有字段的getter/setter/Builder/序列化；验证向后兼容性",
      "contextObtain": "PRD v0.1.6 US-004 AC2；SDS v0.1.6 4.2.2节请求参数表格；需求文档 FR-004(2)"
    },
    {
      "id": "TASK-008",
      "title": "新增 PasswordChangeRequest DTO",
      "description": "在 auth-service 的 dto.request 包下新增 PasswordChangeRequest DTO，包含 oldPassword(@NotBlank)/newPassword(@Size min=8,max=64)/confirmPassword 字段。使用 Lombok 注解。",
      "taskType": "backend",
      "userStoryIds": ["US-004", "US-008"],
      "upstreamTaskIds": [],
      "downstreamTaskIds": ["TASK-031", "TASK-032"],
      "priority": "P0",
      "status": "pending",
      "testMethod": "单元测试验证字段getter/setter/Builder/参数校验/序列化",
      "contextObtain": "PRD v0.1.6 US-004 AC3；SDS v0.1.6 4.2.3节请求参数；需求文档 FR-004(3)"
    },
    {
      "id": "TASK-009",
      "title": "新增 PasswordForgotRequest DTO",
      "description": "在 auth-service 的 dto.request 包下新增 PasswordForgotRequest DTO，包含 mode(EMAIL/SMS)/target/code/newPassword(@Size min=8,max=64) 字段。使用 Lombok 注解。",
      "taskType": "backend",
      "userStoryIds": ["US-004", "US-009"],
      "upstreamTaskIds": [],
      "downstreamTaskIds": ["TASK-031", "TASK-032"],
      "priority": "P1",
      "status": "pending",
      "testMethod": "单元测试验证字段getter/setter/Builder/参数校验/序列化",
      "contextObtain": "PRD v0.1.6 US-004 AC4；SDS v0.1.6 4.2.5节请求参数；需求文档 FR-004(4)"
    },
    {
      "id": "TASK-010",
      "title": "新增 SendVerificationCodeRequest DTO",
      "description": "在 auth-service 的 dto.request 包下新增 SendVerificationCodeRequest DTO，包含 target(手机号或邮箱)/purpose(REGISTER/LOGIN/RESET_PASSWORD/CHANGE_PHONE)/mode(SMS/EMAIL) 字段。使用 Lombok 注解。",
      "taskType": "backend",
      "userStoryIds": ["US-004", "US-016"],
      "upstreamTaskIds": [],
      "downstreamTaskIds": ["TASK-029", "TASK-033"],
      "priority": "P0",
      "status": "pending",
      "testMethod": "单元测试验证字段getter/setter/Builder/序列化",
      "contextObtain": "PRD v0.1.6 US-004 AC5；SDS v0.1.6 4.2.8节请求参数；需求文档 FR-004(5)"
    },
    {
      "id": "TASK-011",
      "title": "新增 PhoneChangeRequest DTO",
      "description": "在 auth-service 的 dto.request 包下新增 PhoneChangeRequest DTO，包含 newPhone/oldPhoneCode（条件必填）/newPhoneCode/emailCode（条件必填）字段。使用 Lombok 注解。",
      "taskType": "backend",
      "userStoryIds": ["US-004", "US-010"],
      "upstreamTaskIds": [],
      "downstreamTaskIds": ["TASK-031", "TASK-032"],
      "priority": "P1",
      "status": "pending",
      "testMethod": "单元测试验证字段getter/setter/Builder/序列化",
      "contextObtain": "PRD v0.1.6 US-004 AC6；SDS v0.1.6 4.2.6节请求参数；需求文档 FR-004(6)"
    },
    {
      "id": "TASK-012",
      "title": "新增 AccountSettlementRequest DTO",
      "description": "在 auth-service 的 dto.request 包下新增 AccountSettlementRequest DTO，包含 userId/loginName（PHONE_SET_USERNAME模式必填）/password（OAUTH_SET_INFO模式必填）/phone（OAUTH_SET_INFO模式必填）/smsCode（OAUTH_SET_INFO模式必填）字段。使用 Lombok 注解。",
      "taskType": "backend",
      "userStoryIds": ["US-004", "US-005"],
      "upstreamTaskIds": [],
      "downstreamTaskIds": ["TASK-026", "TASK-027", "TASK-031", "TASK-032"],
      "priority": "P0",
      "status": "pending",
      "testMethod": "单元测试验证字段getter/setter/Builder/序列化",
      "contextObtain": "PRD v0.1.6 US-004 AC7；SDS v0.1.6 4.2.7节请求参数；需求文档 FR-004(7)"
    },
    {
      "id": "TASK-013",
      "title": "新增 AuthResult + RegisterResult 策略结果DTO",
      "description": "在 auth-service 的 dto.result 包下新增 AuthResult（含 userId/tenantId/loginName/userName/phone/roles/permissions）和 RegisterResult（含 userId/loginName/userName/accountSettled/tokenPair）策略结果DTO。使用 Lombok 注解。",
      "taskType": "backend",
      "userStoryIds": ["US-007"],
      "upstreamTaskIds": [],
      "downstreamTaskIds": ["TASK-017", "TASK-022", "TASK-028"],
      "priority": "P0",
      "status": "pending",
      "testMethod": "单元测试验证字段getter/setter/Builder/序列化",
      "contextObtain": "PRD v0.1.6 US-007 AC2；SDS v0.1.6 4.2节接口规范；需求文档 FR-007"
    },
    {
      "id": "TASK-014",
      "title": "新增 OAuthAccountEntity + OAuthAccountMapper",
      "description": "新增 OAuthAccountEntity 实体（映射 t_auth_oauth_account 表，继承 BaseEntity）和 OAuthAccountMapper（继承 BaseMapper，提供 selectByUserId/selectByProviderAndOpenId 方法）。",
      "taskType": "backend",
      "userStoryIds": ["US-011"],
      "upstreamTaskIds": ["TASK-036"],
      "downstreamTaskIds": ["TASK-021", "TASK-025", "TASK-027"],
      "priority": "P0",
      "status": "pending",
      "testMethod": "单元测试验证 Entity 字段映射正确；验证 Mapper 基础 CRUD 和自定义查询方法",
      "contextObtain": "PRD v0.1.6 US-011「OAuth 账号关联表」；SDS v0.1.6 3.2.1节表结构设计；需求文档 FR-011"
    },
    {
      "id": "TASK-015",
      "title": "新增 VerificationCodeEntity + VerificationCodeMapper",
      "description": "新增 VerificationCodeEntity 实体（映射 t_auth_verification_code 表，继承 BaseEntity）和 VerificationCodeMapper（继承 BaseMapper，提供 selectLatestByTargetAndPurpose/updateUsedStatus/deleteExpired 方法）。",
      "taskType": "backend",
      "userStoryIds": ["US-012"],
      "upstreamTaskIds": ["TASK-036"],
      "downstreamTaskIds": ["TASK-029"],
      "priority": "P0",
      "status": "pending",
      "testMethod": "单元测试验证 Entity 字段映射正确；验证 Mapper 自定义查询方法",
      "contextObtain": "PRD v0.1.6 US-012「验证码记录表」；SDS v0.1.6 3.2.2节表结构设计；需求文档 FR-012"
    },
    {
      "id": "TASK-016",
      "title": "UserEntity扩展（新增字段）",
      "description": "在现有 UserEntity 中新增 registerMode(VARCHAR(32),默认USERNAME)/accountSettled(TINYINT,默认1)/phoneVerified(TINYINT,默认0)/emailVerified(TINYINT,默认0)/lastPasswordChangeTime(DATETIME) 字段。使用 @TableField 注解映射。",
      "taskType": "backend",
      "userStoryIds": ["US-013"],
      "upstreamTaskIds": ["TASK-036"],
      "downstreamTaskIds": ["TASK-018", "TASK-019", "TASK-020", "TASK-023", "TASK-024", "TASK-025", "TASK-026", "TASK-027", "TASK-031"],
      "priority": "P0",
      "status": "pending",
      "testMethod": "单元测试验证新增字段正确性和默认值；验证 Entity 序列化/反序列化",
      "contextObtain": "PRD v0.1.6 US-013「用户表扩展」；SDS v0.1.6 3.2.3节表扩展设计；需求文档 FR-013"
    },
    {
      "id": "TASK-017",
      "title": "LoginStrategy接口 + LoginStrategyFactory",
      "description": "在 strategy 包下新增 LoginStrategy 接口（定义 authenticate(LoginRequest)返回 AuthResult）和 LoginStrategyFactory（构造器注入所有实现，提供 getStrategy(String loginMode)方法，未找到时抛出 LOGIN_MODE_INVALID）。",
      "taskType": "backend",
      "userStoryIds": ["US-006", "US-007"],
      "upstreamTaskIds": ["TASK-002", "TASK-006"],
      "downstreamTaskIds": ["TASK-018", "TASK-019", "TASK-020", "TASK-021", "TASK-028"],
      "priority": "P0",
      "status": "pending",
      "testMethod": "单元测试验证接口定义、工厂类有效 mode 返回对应策略、无效 mode 抛出异常；覆盖率≥90%",
      "contextObtain": "PRD v0.1.6 US-006 AC6、US-007；SDS v0.1.6 1.3.1节多模式登录流程；需求文档 FR-006/FR-007"
    },
    {
      "id": "TASK-018",
      "title": "UsernamePasswordStrategy实现",
      "description": "实现 LoginStrategy 接口处理 USERNAME_PASSWORD 模式。校验 loginName+password，查询租户/用户，BCrypt 校验密码，返回 AuthResult。与 v0.1.5 现有登录逻辑向后兼容。",
      "taskType": "backend",
      "userStoryIds": ["US-006"],
      "upstreamTaskIds": ["TASK-017"],
      "downstreamTaskIds": ["TASK-028"],
      "priority": "P0",
      "status": "pending",
      "testMethod": "单元测试覆盖：登录成功、密码错误、用户不存在、密码为null等场景；覆盖率≥90%",
      "contextObtain": "PRD v0.1.6 US-006 AC1；SDS v0.1.6 1.3.1节多模式登录流程；现有 LoginServiceImpl.java login 方法逻辑"
    },
    {
      "id": "TASK-019",
      "title": "PhoneCodeLoginStrategy实现",
      "description": "实现 LoginStrategy 接口处理 PHONE_CODE 模式。校验 phone+smsCode，通过 VerificationCodeManager.verifyCode 校验验证码，通过手机号查询用户，返回 AuthResult。",
      "taskType": "backend",
      "userStoryIds": ["US-006"],
      "upstreamTaskIds": ["TASK-017"],
      "downstreamTaskIds": ["TASK-028"],
      "priority": "P0",
      "status": "pending",
      "testMethod": "单元测试覆盖：验证码正确登录成功、验证码无效、验证码过期、手机号不存在；覆盖率≥90%",
      "contextObtain": "PRD v0.1.6 US-006 AC2；SDS v0.1.6 1.3.1节多模式登录流程"
    },
    {
      "id": "TASK-020",
      "title": "PhonePasswordLoginStrategy实现",
      "description": "实现 LoginStrategy 接口处理 PHONE_PASSWORD 模式。校验 phone+password，BCrypt 校验密码，通过手机号查询用户，返回 AuthResult。",
      "taskType": "backend",
      "userStoryIds": ["US-006"],
      "upstreamTaskIds": ["TASK-017"],
      "downstreamTaskIds": ["TASK-028"],
      "priority": "P0",
      "status": "pending",
      "testMethod": "单元测试覆盖：密码正确登录成功、密码错误、手机号不存在；覆盖率≥90%",
      "contextObtain": "PRD v0.1.6 US-006 AC3；SDS v0.1.6 1.3.1节多模式登录流程"
    },
    {
      "id": "TASK-021",
      "title": "OAuthLoginStrategy实现",
      "description": "实现 LoginStrategy 接口处理 OAUTH 模式。校验 oauthProvider+oauthCode，通过 OAuthAccountMapper 查询平台用户绑定关系，未绑定时返回 OAUTH_ACCOUNT_NOT_BOUND，返回 AuthResult。",
      "taskType": "backend",
      "userStoryIds": ["US-006"],
      "upstreamTaskIds": ["TASK-003", "TASK-014", "TASK-017"],
      "downstreamTaskIds": ["TASK-028"],
      "priority": "P0",
      "status": "pending",
      "testMethod": "单元测试覆盖：OAuth账号已绑定登录成功、未绑定、提供商无效；覆盖率≥90%",
      "contextObtain": "PRD v0.1.6 US-006 AC4；SDS v0.1.6 1.3.1节多模式登录流程"
    },
    {
      "id": "TASK-022",
      "title": "RegisterStrategy接口 + RegisterStrategyFactory",
      "description": "在 strategy 包下新增 RegisterStrategy 接口（定义 register(RegisterRequest)方法）和 RegisterStrategyFactory（构造器注入所有实现，提供 getStrategy(String registerMode)方法，未找到时抛出 REGISTER_MODE_INVALID）。",
      "taskType": "backend",
      "userStoryIds": ["US-005", "US-007"],
      "upstreamTaskIds": ["TASK-001", "TASK-007"],
      "downstreamTaskIds": ["TASK-023", "TASK-024", "TASK-025", "TASK-026", "TASK-027"],
      "priority": "P0",
      "status": "pending",
      "testMethod": "单元测试验证接口定义、工厂类有效 mode 返回对应策略、无效 mode 抛出异常；覆盖率≥90%",
      "contextObtain": "PRD v0.1.6 US-005 AC7、US-007；SDS v0.1.6 1.3.2节多模式注册流程；需求文档 FR-005/FR-007"
    },
    {
      "id": "TASK-023",
      "title": "UsernamePwdRegisterStrategy实现",
      "description": "实现 RegisterStrategy 接口处理 USERNAME 模式。校验 loginName+password+phone，校验用户名/手机号唯一性，BCrypt 加密密码，创建完整用户（account_settled=true），返回 UserDTO。与 v0.1.5 现有注册逻辑向后兼容。",
      "taskType": "backend",
      "userStoryIds": ["US-005"],
      "upstreamTaskIds": ["TASK-016", "TASK-022"],
      "downstreamTaskIds": ["TASK-028"],
      "priority": "P0",
      "status": "pending",
      "testMethod": "单元测试覆盖：注册成功、用户名已存在、手机号已存在；覆盖率≥90%",
      "contextObtain": "PRD v0.1.6 US-005 AC1；SDS v0.1.6 1.3.2节多模式注册流程"
    },
    {
      "id": "TASK-024",
      "title": "PhoneCodeRegisterStrategy实现",
      "description": "实现 RegisterStrategy 接口处理 PHONE_CODE 模式。校验 phone+smsCode，校验手机号唯一性，VerificationCodeManager 校验验证码，自动生成 loginName，创建用户（account_settled=false），返回 RegisterResult（含 TokenPairDTO 自动登录）。",
      "taskType": "backend",
      "userStoryIds": ["US-005"],
      "upstreamTaskIds": ["TASK-015", "TASK-022"],
      "downstreamTaskIds": ["TASK-028"],
      "priority": "P0",
      "status": "pending",
      "testMethod": "单元测试覆盖：注册成功（含自动登录返回Token）、验证码错误、手机号已存在；覆盖率≥90%",
      "contextObtain": "PRD v0.1.6 US-005 AC2；SDS v0.1.6 1.3.2节多模式注册流程"
    },
    {
      "id": "TASK-025",
      "title": "OAuthRegisterStrategy实现",
      "description": "实现 RegisterStrategy 接口处理 OAUTH 模式。校验 oauthProvider+oauthCode，获取用户信息，校验 openId 全局唯一，创建用户（account_settled=false）+ OAuth 账号绑定记录，返回 RegisterResult（含 TokenPairDTO 自动登录）。",
      "taskType": "backend",
      "userStoryIds": ["US-005"],
      "upstreamTaskIds": ["TASK-003", "TASK-014", "TASK-022"],
      "downstreamTaskIds": ["TASK-028"],
      "priority": "P0",
      "status": "pending",
      "testMethod": "单元测试覆盖：注册成功（含OAuth绑定+自动登录）、OAuth账号已被绑定；覆盖率≥90%",
      "contextObtain": "PRD v0.1.6 US-005 AC3；SDS v0.1.6 1.3.2节多模式注册流程"
    },
    {
      "id": "TASK-026",
      "title": "PhoneSetUsernameStrategy实现",
      "description": "实现 RegisterStrategy 接口处理 PHONE_SET_USERNAME 模式（两步注册第一步）。校验 phone+smsCode，VerificationCodeManager 校验验证码，创建临时用户（account_settled=false），返回 RegisterResult（含 TokenPairDTO 自动登录）。",
      "taskType": "backend",
      "userStoryIds": ["US-005"],
      "upstreamTaskIds": ["TASK-015", "TASK-022"],
      "downstreamTaskIds": ["TASK-031", "TASK-032"],
      "priority": "P1",
      "status": "pending",
      "testMethod": "单元测试覆盖：两步注册第一步成功（含自动登录）、验证码错误；覆盖率≥90%",
      "contextObtain": "PRD v0.1.6 US-005 AC4；SDS v0.1.6 1.3.2节多模式注册流程"
    },
    {
      "id": "TASK-027",
      "title": "OAuthSetInfoStrategy实现",
      "description": "实现 RegisterStrategy 接口处理 OAUTH_SET_INFO 模式（两步注册第一步）。校验 oauthProvider+oauthCode，获取用户信息，校验 openId 唯一，创建临时用户+OAuth 账号绑定，返回 RegisterResult（含 TokenPairDTO 自动登录）。",
      "taskType": "backend",
      "userStoryIds": ["US-005"],
      "upstreamTaskIds": ["TASK-003", "TASK-014", "TASK-022"],
      "downstreamTaskIds": ["TASK-031", "TASK-032"],
      "priority": "P1",
      "status": "pending",
      "testMethod": "单元测试覆盖：两步注册第一步成功（含OAuth绑定+自动登录）、OAuth账号已被绑定；覆盖率≥90%",
      "contextObtain": "PRD v0.1.6 US-005 AC5；SDS v0.1.6 1.3.2节多模式注册流程"
    },
    {
      "id": "TASK-028",
      "title": "AuthenticationService 统一认证编排服务",
      "description": "新增统一认证编排服务 AuthenticationService。authenticate()方法编排：策略校验→AuthResult→校验租户状态→校验用户状态(含account_settled)→构建LoginUserDTO→JWT双Token签发→同端互斥→Redis登录态→缓存状态→登录日志→最后登录时间/IP→返回TokenPairDTO。register()方法调用RegisterStrategyFactory。",
      "taskType": "backend",
      "userStoryIds": ["US-007"],
      "upstreamTaskIds": ["TASK-017", "TASK-018", "TASK-019", "TASK-020", "TASK-021"],
      "downstreamTaskIds": ["TASK-032"],
      "priority": "P0",
      "status": "pending",
      "testMethod": "单元测试覆盖4种登录模式的完整编排流程；验证account_settled=false时返回ACCOUNT_NOT_SETTLED；覆盖率≥85%",
      "contextObtain": "PRD v0.1.6 US-007「统一认证服务层」；SDS v0.1.6 1.3.1节多模式登录流程；需求文档 FR-007"
    },
    {
      "id": "TASK-029",
      "title": "VerificationCodeManager 验证码管理服务",
      "description": "新增 VerificationCodeManager 服务。核心方法：generateCode(target,mode,purpose)生成6位验证码写入Redis+DB；verifyCode(target,code,purpose)校验验证码后标记used=1；isSendTooFrequent(target,purpose)频控检查(60秒间隔)；cleanExpiredCodes()清理过期记录。",
      "taskType": "backend",
      "userStoryIds": ["US-016"],
      "upstreamTaskIds": ["TASK-005", "TASK-015"],
      "downstreamTaskIds": ["TASK-019", "TASK-024", "TASK-026", "TASK-031"],
      "priority": "P0",
      "status": "pending",
      "testMethod": "单元测试覆盖：验证码生成成功、校验通过、过期、已使用、频率控制、target为null；覆盖率≥90%",
      "contextObtain": "PRD v0.1.6 US-016「验证码管理服务」；SDS v0.1.6 1.3.3节验证码生命周期管理；需求文档 FR-016"
    },
    {
      "id": "TASK-030",
      "title": "VerificationCodeService 验证码发送服务（接口+模拟实现）",
      "description": "新增 VerificationCodeService 接口（sendSmsCode/sendEmailCode方法）和 SimulatedVerificationCodeService 模拟实现（日志输出验证码内容，@ConditionalOnProperty mock=true 条件装配）。",
      "taskType": "backend",
      "userStoryIds": ["US-015"],
      "upstreamTaskIds": [],
      "downstreamTaskIds": ["TASK-029"],
      "priority": "P1",
      "status": "pending",
      "testMethod": "单元测试验证接口定义；验证模拟实现日志输出正确；验证配置mock=true时自动装配",
      "contextObtain": "PRD v0.1.6 US-015「验证码发送服务」；SDS v0.1.6 2.2.2节 VerificationCodeService 描述；需求文档 FR-015"
    },
    {
      "id": "TASK-031",
      "title": "PasswordService 密码管理服务",
      "description": "新增 PasswordService 服务。changePassword：校验原密码/新密码一致性/新密码复杂度→BCrypt加密→更新DB→清理Redis登录态。forgotPasswordSendCode：校验账号存在→生成验证码并发送。forgotPasswordReset：校验验证码→BCrypt加密→更新DB→清理Redis登录态。",
      "taskType": "backend",
      "userStoryIds": ["US-008", "US-009"],
      "upstreamTaskIds": ["TASK-008", "TASK-009", "TASK-016", "TASK-029"],
      "downstreamTaskIds": ["TASK-032"],
      "priority": "P0",
      "status": "pending",
      "testMethod": "单元测试覆盖修改密码成功/原密码错误/新密码与旧密码相同；密码找回发送验证码成功/重置成功/验证码错误/过期；验证密码修改后清理登录态；覆盖率≥85%",
      "contextObtain": "PRD v0.1.6 US-008/US-009；SDS v0.1.6 4.2.3/4.2.4/4.2.5节；需求文档 FR-008/FR-009"
    },
    {
      "id": "TASK-032",
      "title": "AuthController扩展（新增密码管理/手机号变更/账号完善等端点）",
      "description": "扩展现有 AuthController：修改 login/register 端点适配新 DTO；新增 PUT /password/change、POST /password/forgot/send-code、POST /password/forgot/reset、PUT /phone/change、PUT /account/settlement 等端点。使用 @Valid 校验，返回 ApiResult<T>。",
      "taskType": "backend",
      "userStoryIds": ["US-005", "US-006", "US-008", "US-009", "US-010"],
      "upstreamTaskIds": ["TASK-006", "TASK-007", "TASK-008", "TASK-009", "TASK-011", "TASK-012", "TASK-028", "TASK-031"],
      "downstreamTaskIds": [],
      "priority": "P0",
      "status": "pending",
      "testMethod": "MockMvc 单元测试覆盖每个新增/修改端点的成功和错误场景；覆盖率≥80%",
      "contextObtain": "PRD v0.1.6 US-005~US-010 API定义；SDS v0.1.6 4.2节全部API定义；需求文档附录A"
    },
    {
      "id": "TASK-033",
      "title": "验证码发送Controller端点",
      "description": "在 AuthController 新增 POST /api/v1/auth/verification-code/send 端点。接收 SendVerificationCodeRequest，调用 VerificationCodeManager 检查频率→生成验证码→发送→返回成功。白名单路径，无需登录。",
      "taskType": "backend",
      "userStoryIds": ["US-016"],
      "upstreamTaskIds": ["TASK-010", "TASK-029"],
      "downstreamTaskIds": [],
      "priority": "P0",
      "status": "pending",
      "testMethod": "MockMvc 单元测试覆盖：发送成功、发送频率过高、参数校验失败；覆盖率≥80%",
      "contextObtain": "SDS v0.1.6 4.2.8节「发送验证码」接口定义；需求文档 FR-016"
    },
    {
      "id": "TASK-034",
      "title": "SecurityConfig白名单扩展",
      "description": "在 SecurityConfig 中将 /api/v1/auth/verification-code/send、/api/v1/auth/password/forgot/send-code、/api/v1/auth/password/forgot/reset 加入匿名访问白名单。同步更新网关白名单配置（如存在）。",
      "taskType": "backend",
      "userStoryIds": ["US-005", "US-009", "US-016"],
      "upstreamTaskIds": [],
      "downstreamTaskIds": ["TASK-032", "TASK-033"],
      "priority": "P0",
      "status": "pending",
      "testMethod": "验证 SecurityConfig 中白名单路径正确；验证匿名访问新增路径返回正确响应（非401/403）",
      "contextObtain": "SDS v0.1.6 8.3节网关白名单列表；现有 SecurityConfig.java；网关 application.yml"
    },
    {
      "id": "TASK-035",
      "title": "验证码相关配置项（application.yml扩展）",
      "description": "在 auth-service 的 application.yml 中新增 verification-code.mock/expire-seconds/send-interval-seconds/length 和 password.min-length/max-length 配置项。创建对应的 @ConfigurationProperties 配置属性类。",
      "taskType": "backend",
      "userStoryIds": ["US-015", "US-016"],
      "upstreamTaskIds": [],
      "downstreamTaskIds": ["TASK-029", "TASK-030"],
      "priority": "P0",
      "status": "pending",
      "testMethod": "单元测试验证配置属性类正确加载配置值；验证默认值正确",
      "contextObtain": "SDS v0.1.6 8.1节配置项表；需求文档5.2节新增/变更配置"
    },
    {
      "id": "TASK-036",
      "title": "数据库DDL脚本（新表创建 + 表扩展ALTER）",
      "description": "创建 scripts/sql/auth-init-v0.1.6.sql 脚本。包含：新建 t_auth_oauth_account 表（含 uk_provider_openid 唯一索引）、新建 t_auth_verification_code 表（含 idx_target_purpose/idx_expire_time 索引）、ALTER TABLE t_auth_user 新增5个扩展字段。",
      "taskType": "docs",
      "userStoryIds": ["US-011", "US-012", "US-013"],
      "upstreamTaskIds": [],
      "downstreamTaskIds": ["TASK-014", "TASK-015", "TASK-016"],
      "priority": "P0",
      "status": "pending",
      "testMethod": "验证 SQL 语法正确；验证 t_auth_user 扩展字段默认值兼容 v0.1.5 数据；验证索引命名规范",
      "contextObtain": "PRD v0.1.6 US-011/US-012/US-013；SDS v0.1.6 3.2节全部数据设计；需求文档 FR-011/FR-012/FR-013"
    }
  ]
}